redbaron/__init__.py
redbaron/base_nodes.py
redbaron/nodes.py
redbaron/private_config.py
redbaron/redbaron.py
redbaron/syntax_highlight.py
redbaron/utils.py
redbaron-0.9.2.dist-info/DESCRIPTION.rst
redbaron-0.9.2.dist-info/METADATA
redbaron-0.9.2.dist-info/RECORD
redbaron-0.9.2.dist-info/WHEEL
redbaron-0.9.2.dist-info/metadata.json
redbaron-0.9.2.dist-info/top_level.txt
