Metadata-Version: 2.1
Name: redbaron
Version: 0.9.2
Summary: Abstraction on top of baron, a FST for python to make writing refactoring code a realistic task
Home-page: https://github.com/PyCQA/redbaron
Author: Laurent Peuch
Author-email: cortex@worlddomination.be
License: lgplv3+
Keywords: baron fst ast refactoring
Platform: UNKNOWN
Classifier: Development Status :: 3 - Alpha
Classifier: Intended Audience :: Developers
Classifier: Programming Language :: Python :: 2
Classifier: Programming Language :: Python :: 2.7
Classifier: Programming Language :: Python :: 3
Classifier: Programming Language :: Python :: 3.3
Classifier: Programming Language :: Python :: 3.4
Classifier: License :: OSI Approved :: GNU Lesser General Public License v3 (LGPLv3)
Classifier: Topic :: Software Development
Classifier: Topic :: Software Development :: Code Generators
Classifier: Topic :: Software Development :: Libraries
Provides-Extra: notebook
